<annotation>
    <folder>core50_images_sample</folder>
    <filename>C_03_19_265.jpg</filename>
    <size>
        <width>350</width>
        <height>350</height>
        <depth>3</depth>
    </size>
    <segmented>0</segmented>
    <object>
        <name>hand</name>
        <pose>Unspecified</pose>
        <truncated>0</truncated>
        <occluded>0</occluded>
        <difficult>0</difficult>
        <polygon>
            <x1>3</x1>
            <y1>181</y1>
            <x2>78</x2>
            <y2>192</y2>
            <x3>111</x3>
            <y3>191</y3>
            <x4>117</x4>
            <y4>194</y4>
            <x5>129</x5>
            <y5>193</y5>
            <x6>137</x6>
            <y6>189</y6>
            <x7>170</x7>
            <y7>181</y7>
            <x8>198</x8>
            <y8>173</y8>
            <x9>208</x9>
            <y9>179</y9>
            <x10>226</x10>
            <y10>196</y10>
            <x11>228</x11>
            <y11>208</y11>
            <x12>225</x12>
            <y12>211</y12>
            <x13>219</x13>
            <y13>202</y13>
            <x14>207</x14>
            <y14>192</y14>
            <x15>187</x15>
            <y15>192</y15>
            <x16>189</x16>
            <y16>197</y16>
            <x17>208</x17>
            <y17>208</y17>
            <x18>218</x18>
            <y18>217</y18>
            <x19>224</x19>
            <y19>227</y19>
            <x20>224</x20>
            <y20>231</y20>
            <x21>217</x21>
            <y21>230</y21>
            <x22>204</x22>
            <y22>217</y22>
            <x23>191</x23>
            <y23>210</y23>
            <x24>176</x24>
            <y24>211</y24>
            <x25>173</x25>
            <y25>222</y25>
            <x26>189</x26>
            <y26>220</y26>
            <x27>189</x27>
            <y27>229</y27>
            <x28>180</x28>
            <y28>233</y28>
            <x29>163</x29>
            <y29>233</y29>
            <x30>148</x30>
            <y30>234</y30>
            <x31>127</x31>
            <y31>223</y31>
            <x32>81</x32>
            <y32>224</y32>
            <x33>2</x33>
            <y33>240</y33>
            <x34>3</x34>
            <y34>180</y34>
        </polygon>
        <bndbox>
            <xmin>2</xmin>
            <ymin>173</ymin>
            <xmax>228</xmax>
            <ymax>240</ymax>
        </bndbox>
    </object>
</annotation>